{"cfs":{"annual":{"2024":{"asset":24795.6,"ca":13708.9,"cash":3387.9,"nca":10985.8,"equity":15223.6,"cl":8155.5,"liab":9571.9,"ncl":1416.4,"op":-484.0,"gp":2294.6,"np":-321.2,"pretax":-689.2,"rev":20453.6,"cff":-2428.4,"cfi":-895.8,"capex_intan":22.4,"capex_ppe":946.2,"cfo":4026.5},"2023":{"asset":28253.4,"ca":17873.2,"cash":2627.8,"nca":10380.2,"equity":16177.8,"cl":8650.7,"liab":12075.6,"ncl":3424.9,"op":854.8,"gp":1839.7,"np":476.2,"pretax":589.9,"rev":18812.0,"cff":1742.8,"cfi":-127.2,"capex_intan":27.4,"capex_ppe":462.0,"cfo":-766.7},"2022":{"ca":11896.9,"cash":1801.8,"nca":7356.6,"asset":19253.5,"cl":4130.4,"ncl":994.9,"liab":5125.4,"equity":14128.1,"rev":16843.7,"gp":2580.5,"op":1609.2,"pretax":1522.4,"np":1059.5,"cfo":1752.1,"cfi":-1158.0,"capex_ppe":694.5,"capex_intan":36.8,"cff":-1547.4},"2021":{"ca":11264.8,"cash":2770.2,"nca":7779.7,"asset":19044.4,"cl":3775.1,"ncl":1265.8,"liab":5040.9,"equity":14003.5,"rev":15649.4,"gp":2781.0,"op":1889.4,"pretax":1798.4,"np":1483.2,"cfo":562.9,"cfi":-1512.4,"capex_ppe":385.3,"capex_intan":31.4,"cff":-555.7},"2020":{"ca":10842.3,"cash":4225.3,"nca":7151.7,"asset":17994.0,"cl":3551.8,"ncl":1647.1,"liab":5198.9,"equity":12795.1,"rev":15511.7,"gp":2740.3,"op":1673.3,"pretax":1573.7,"np":1186.4,"cfo":3350.7,"cfi":-487.9,"capex_ppe":294.8,"capex_intan":26.7,"cff":-677.7},"2019":{"ca":10984.6,"cash":2089.8,"nca":7074.5,"asset":18059.1,"cl":6653.3,"ncl":285.1,"liab":6938.4,"equity":11120.7,"rev":15777.5,"gp":3173.8,"op":2142.1,"pretax":1969.5,"np":1469.7,"cfo":77.0,"cfi":-779.5,"capex_ppe":419.4,"capex_intan":54.1,"cff":-500.3},"2018":{"ca":9585.7,"cash":3293.1,"nca":7019.6,"asset":16605.3,"cl":4048.4,"ncl":2527.0,"liab":6575.4,"equity":10029.9,"rev":15600.6,"gp":3277.3,"op":2343.6,"pretax":2242.4,"np":1696.7,"cfo":381.9,"cfi":-1625.6,"capex_ppe":381.4,"capex_intan":30.2,"cff":-1339.2},"2017":{"ca":11331.0,"cash":5858.7,"nca":6777.1,"asset":18108.1,"cl":5409.5,"ncl":2850.1,"liab":8259.5,"equity":9848.5,"rev":19203.8,"gp":3250.9,"op":2360.9,"pretax":2651.7,"np":2033.4,"cfo":3765.9,"cfi":-528.7,"capex_ppe":823.4,"capex_intan":15.3,"cff":-59.8},"2016":{"ca":8237.5,"cash":2764.1,"nca":6815.1,"asset":15052.6,"cl":4571.8,"ncl":2724.5,"liab":7296.3,"equity":7756.3,"rev":13197.5,"gp":1936.1,"op":1208.1,"pretax":1052.8,"np":795.6,"cfo":1644.5,"cfi":-769.6,"capex_ppe":289.0,"capex_intan":18.8,"cff":-582.0}},"quarter":{"25Q1":{"asset":24433.8,"ca":13252.7,"cash":3251.6,"nca":11080.3,"equity":15215.7,"cl":7396.7,"liab":9218.1,"ncl":1821.4,"op":290.5,"gp":568.4,"np":215.1,"pretax":283.1,"rev":3983.9,"cff":199.3,"cfi":-455.7,"capex_intan":7.9,"capex_ppe":209.2,"cfo":107.9},"25Q2":{"asset":23758.7,"ca":13006.8,"cash":3132.7,"nca":10651.0,"equity":14939.5,"cl":6849.6,"liab":8819.2,"ncl":1969.7,"op":211.2,"gp":447.6,"np":25.7,"pretax":51.5,"rev":4449.9,"cff":96.3,"cfi":-123.8,"capex_intan":9.8,"capex_ppe":250.8,"cfo":0.8},"25Q3":{"asset":23290.4,"ca":12334.5,"cash":2959.4,"nca":10855.0,"equity":15102.1,"cl":6312.6,"liab":8188.2,"ncl":1875.7,"op":267.0,"gp":469.4,"np":236.0,"pretax":314.2,"rev":3940.2,"cff":-1355.7,"cfi":-133.3,"capex_intan":6.5,"capex_ppe":281.7,"cfo":1251.0},"26Q1":{"asset":22884.9,"ca":12078.9,"cash":3867.7,"nca":10700.8,"equity":15309.9,"cl":6109.4,"liab":7575.0,"ncl":1462.8,"op":154.5,"gp":420.1,"np":204.3,"pretax":221.5,"rev":3611.5,"cff":-399.1,"cfi":18.1,"capex_intan":3.6,"capex_ppe":77.0,"cfo":1276.8}}},"ofs":{"annual":{"2024":{"asset":13926.7,"ca":5862.9,"cash":680.9,"nca":8063.8,"equity":8196.8,"cl":4986.4,"liab":5729.9,"ncl":743.5,"op":-1042.7,"gp":969.9,"np":-1065.2,"pretax":-1408.5,"rev":9712.6,"cff":-1781.4,"cfi":-171.7,"capex_intan":8.4,"capex_ppe":212.6,"cfo":2308.1},"2023":{"asset":16766.5,"ca":9077.4,"cash":320.1,"nca":7689.1,"equity":9976.3,"cl":4135.9,"liab":6790.3,"ncl":2654.3,"op":583.8,"gp":1134.2,"np":365.0,"pretax":408.0,"rev":10179.4,"cff":2097.3,"cfi":-2227.9,"capex_intan":23.2,"capex_ppe":82.1,"cfo":-359.3},"2022":{"ca":7688.6,"cash":813.9,"nca":5688.9,"asset":13377.5,"cl":2990.2,"ncl":50.2,"liab":3040.4,"equity":10337.1,"rev":8508.5,"gp":1627.3,"op":960.8,"pretax":968.6,"np":757.7,"cfo":484.1,"cfi":114.8,"capex_ppe":123.9,"capex_intan":21.5,"cff":-1037.0},"2021":{"ca":6715.1,"cash":1257.3,"nca":6216.6,"asset":12931.7,"cl":2215.2,"ncl":73.6,"liab":2288.8,"equity":10642.9,"rev":7838.3,"gp":1578.0,"op":945.2,"pretax":872.9,"np":694.0,"cfo":-396.2,"cfi":-752.4,"capex_ppe":109.9,"capex_intan":19.8,"cff":-444.9},"2020":{"ca":7633.8,"cash":2841.3,"nca":5488.0,"asset":13121.8,"cl":2642.7,"ncl":81.6,"liab":2724.4,"equity":10397.4,"rev":8354.1,"gp":1838.4,"op":1057.3,"pretax":1365.1,"np":1135.5,"cfo":2153.0,"cfi":-588.4,"capex_ppe":17.5,"capex_intan":16.6,"cff":572.6},"2019":{"ca":7020.9,"cash":726.3,"nca":4891.2,"asset":11912.1,"cl":3074.6,"ncl":127.8,"liab":3202.4,"equity":8709.7,"rev":8608.5,"gp":2336.3,"op":1559.3,"pretax":2132.6,"np":1623.9,"cfo":-635.4,"cfi":-316.6,"capex_ppe":17.4,"capex_intan":32.8,"cff":-427.1},"2018":{"ca":6090.9,"cash":2107.3,"nca":4331.3,"asset":10422.2,"cl":2895.8,"ncl":14.4,"liab":2910.3,"equity":7512.0,"rev":9443.1,"gp":2422.2,"op":1772.2,"pretax":1880.7,"np":1425.8,"cfo":-6.9,"cfi":-1076.8,"capex_ppe":18.3,"capex_intan":13.2,"cff":-1316.7},"2017":{"ca":8406.9,"cash":4507.4,"nca":3758.1,"asset":12165.0,"cl":4325.4,"ncl":259.0,"liab":4584.4,"equity":7580.7,"rev":13138.6,"gp":2464.4,"op":1920.0,"pretax":2388.6,"np":1787.6,"cfo":2634.5,"cfi":331.1,"capex_ppe":24.3,"capex_intan":3.6,"cff":234.2},"2016":{"ca":5054.1,"cash":1336.5,"nca":3701.0,"asset":8755.0,"cl":2980.1,"ncl":160.9,"liab":3141.0,"equity":5614.1,"rev":8499.7,"gp":1604.8,"op":1046.8,"pretax":1148.3,"np":904.6,"cfo":1326.2,"cfi":-878.1,"capex_ppe":63.2,"capex_intan":7.4,"cff":-70.1}},"quarter":{"25Q1":{"asset":13540.8,"ca":5202.2,"cash":288.3,"nca":8338.6,"equity":8122.4,"cl":4589.7,"liab":5418.4,"ncl":828.8,"op":212.2,"gp":383.9,"np":142.0,"pretax":182.9,"rev":1990.3,"cff":227.7,"cfi":-377.8,"capex_intan":1.1,"capex_ppe":161.0,"cfo":-245.1},"25Q2":{"asset":13939.3,"ca":5729.9,"cash":388.0,"nca":8209.4,"equity":8200.4,"cl":4739.6,"liab":5738.9,"ncl":999.3,"op":296.8,"gp":421.7,"np":218.4,"pretax":283.2,"rev":2226.9,"cff":92.2,"cfi":30.6,"capex_intan":0.7,"capex_ppe":161.7,"cfo":-19.7},"25Q3":{"asset":13223.4,"ca":4871.9,"cash":581.1,"nca":8351.4,"equity":8254.9,"cl":4066.9,"liab":4968.5,"ncl":901.5,"op":275.0,"gp":363.2,"np":186.5,"pretax":234.8,"rev":1964.2,"cff":-734.7,"cfi":-87.9,"capex_intan":1.1,"capex_ppe":223.7,"cfo":1011.8},"26Q1":{"asset":13145.7,"ca":4797.5,"cash":506.9,"nca":8348.1,"equity":8371.7,"cl":4268.7,"liab":4774.0,"ncl":505.3,"op":218.3,"gp":357.1,"np":167.5,"pretax":216.2,"rev":1894.7,"cff":-401.2,"cfi":-97.8,"capex_intan":3.5,"capex_ppe":34.7,"cfo":586.5}}},"market":"kr","est":{"2026":{"rev":16797.0,"op":1247.0,"np":925.0}}}