{"cfs":{"annual":{"2025":{"asset":104566.7,"cash":5261.4,"equity":8070.8,"liab":96496.0,"np":438.6,"pretax":548.6,"op":337.2,"rev":17144.5,"cff":847.8,"cfi":1732.1,"capex_intan":45.3,"capex_ppe":35.7,"cfo":-2656.5},"2024":{"asset":96031.7,"cash":5337.0,"equity":7759.9,"liab":88271.8,"op":-749.3,"np":-454.5,"pretax":-542.4,"rev":14425.7,"cff":4028.3,"cfi":-2017.7,"capex_intan":33.2,"capex_ppe":19.1,"cfo":-2709.2},"2023":{"asset":92118.4,"cash":6038.3,"equity":8305.2,"liab":83813.2,"op":-620.0,"np":-113.7,"pretax":57.5,"rev":15083.7,"cff":5082.2,"cfi":2114.8,"capex_intan":83.1,"capex_ppe":23.7,"cfo":-6831.9}},"quarter":{"25Q1":{"asset":99818.4,"cash":4796.5,"equity":7735.1,"liab":92083.3,"np":94.9,"pretax":127.4,"op":60.1,"rev":4371.6,"cff":140.8,"cfi":1818.9,"capex_intan":31.8,"capex_ppe":7.5,"cfo":-2500.3},"25Q2":{"asset":98991.7,"cash":4816.1,"equity":7917.5,"liab":91074.1,"np":223.7,"pretax":272.7,"op":195.7,"rev":5031.8,"cff":-111.2,"cfi":99.2,"capex_intan":4.4,"capex_ppe":6.4,"cfo":30.7},"25Q3":{"asset":110151.4,"cash":9752.6,"equity":8037.5,"liab":102113.9,"np":97.5,"pretax":131.7,"op":115.1,"rev":3009.7,"cff":2665.6,"cfi":-166.8,"capex_intan":3.9,"capex_ppe":11.5,"cfo":2437.9},"25Q4":{"asset":104566.7,"cash":5261.4,"equity":8070.8,"liab":96496.0,"np":22.5,"pretax":16.7,"op":-33.8,"rev":4731.3,"cff":-1847.5,"cfi":-19.3,"capex_intan":5.2,"capex_ppe":10.3,"cfo":-2624.7},"26Q1":{"asset":105532.6,"cash":3008.0,"equity":8073.7,"liab":97458.9,"np":150.4,"pretax":206.7,"op":91.8,"rev":7690.6,"cff":-3403.6,"cfi":22.6,"capex_intan":17.1,"capex_ppe":6.5,"cfo":1130.1}}},"ofs":{"annual":{"2025":{"asset":55216.0,"cash":1911.7,"equity":7006.8,"liab":48209.2,"np":121.1,"pretax":154.9,"op":147.3,"rev":11196.2,"cff":600.9,"cfi":1582.2,"capex_intan":11.6,"capex_ppe":20.1,"cfo":-1786.1},"2024":{"asset":48159.4,"cash":1514.7,"equity":7011.3,"liab":41148.1,"op":-309.4,"np":-242.4,"pretax":-326.5,"rev":8949.5,"cff":4650.4,"cfi":-1999.5,"capex_intan":17.3,"capex_ppe":15.6,"cfo":-3049.8},"2023":{"asset":44119.8,"cash":1913.3,"equity":7362.9,"liab":36756.9,"op":-471.0,"np":837.3,"pretax":971.0,"rev":9496.5,"cff":5212.0,"cfi":2607.9,"capex_intan":7.6,"capex_ppe":11.3,"cfo":-8401.7}},"quarter":{"25Q1":{"asset":52717.1,"cash":2876.0,"equity":6991.9,"liab":45725.2,"np":100.4,"pretax":129.5,"op":126.0,"rev":3040.0,"cff":-311.5,"cfi":1806.3,"capex_intan":3.8,"capex_ppe":6.7,"cfo":-133.5},"25Q2":{"asset":53020.0,"cash":2162.4,"equity":7058.0,"liab":45962.0,"np":65.0,"pretax":83.7,"op":82.7,"rev":3531.8,"cff":36.8,"cfi":2.7,"capex_intan":2.4,"capex_ppe":0.3,"cfo":-753.0},"25Q3":{"asset":59640.5,"cash":2514.2,"equity":7081.0,"liab":52559.5,"np":23.6,"pretax":34.6,"op":34.6,"rev":1542.2,"cff":2582.2,"cfi":-173.2,"capex_intan":2.4,"capex_ppe":6.2,"cfo":-2057.3},"25Q4":{"asset":55216.0,"cash":1911.7,"equity":7006.8,"liab":48209.2,"np":-67.9,"pretax":-92.8,"op":-96.1,"rev":3082.1,"cff":-1706.6,"cfi":-53.6,"capex_intan":3.0,"capex_ppe":6.9,"cfo":1157.7},"26Q1":{"asset":56590.4,"cash":1316.2,"equity":6887.1,"liab":49703.4,"np":53.7,"pretax":73.8,"op":59.0,"rev":6092.7,"cff":-3593.1,"cfi":-47.5,"capex_intan":1.4,"capex_ppe":3.8,"cfo":3045.0}}},"market":"kr","est":{}}