{"cfs":{"annual":{"2025":{"asset":11575.4,"ca":7270.8,"cash":1641.3,"nca":4304.6,"equity":3429.7,"cl":7449.2,"liab":8145.6,"ncl":696.4,"op":695.9,"gp":1319.4,"np":689.5,"pretax":618.4,"rev":7893.4,"cff":-138.5,"cfi":-266.1,"capex_intan":90.5,"capex_ppe":99.1,"cfo":728.7},"2024":{"asset":9688.1,"ca":5552.1,"cash":1314.4,"nca":4136.0,"equity":2765.7,"cl":6284.1,"liab":6922.4,"ncl":638.3,"op":422.4,"gp":985.5,"np":272.2,"pretax":222.6,"rev":7246.1,"cff":219.4,"cfi":-149.0,"capex_intan":91.8,"capex_ppe":91.7,"cfo":367.1},"2023":{"asset":8991.3,"ca":4909.0,"cash":866.2,"nca":4082.3,"equity":2596.3,"cl":5777.2,"liab":6395.0,"ncl":617.8,"op":188.7,"gp":679.0,"np":56.9,"pretax":76.6,"rev":6303.8,"cff":77.8,"cfi":36.6,"capex_intan":72.5,"capex_ppe":86.9,"cfo":-132.8},"2022":{"ca":4684.6,"cash":882.8,"nca":3849.3,"asset":8533.9,"cl":5399.1,"ncl":532.4,"liab":5931.4,"equity":2602.4,"rev":5440.2,"gp":368.8,"op":-88.2,"pretax":-284.1,"np":-266.8,"cfo":265.8,"cfi":-152.2,"capex_ppe":121.9,"capex_intan":4.9,"cff":-278.2},"2021":{"ca":4271.0,"cash":1046.9,"nca":4103.8,"asset":8374.8,"cl":4907.9,"ncl":627.1,"liab":5535.1,"equity":2839.8,"rev":4934.6,"gp":412.3,"op":36.4,"pretax":-20.9,"np":10.1,"cfo":182.0,"cfi":-101.0,"capex_ppe":120.1,"capex_intan":10.9,"cff":-168.5},"2020":{"ca":4387.0,"cash":1133.2,"nca":3705.7,"asset":8092.6,"cl":4806.4,"ncl":621.5,"liab":5427.9,"equity":2664.7,"rev":5866.9,"gp":551.6,"op":143.4,"pretax":172.3,"np":206.5,"cfo":573.9,"cfi":302.1,"capex_ppe":91.4,"capex_intan":4.0,"cff":-386.0},"2019":{"ca":4389.9,"cash":643.9,"nca":3893.9,"asset":8283.8,"cl":3552.7,"ncl":2356.4,"liab":5909.1,"equity":2374.7,"rev":6106.1,"gp":665.2,"op":300.4,"pretax":142.1,"np":203.8,"cfo":729.1,"cfi":141.1,"capex_ppe":87.8,"capex_intan":1.7,"cff":-730.5},"2018":{"ca":4938.2,"cash":503.9,"nca":3703.3,"asset":8641.5,"cl":3498.7,"ncl":2930.7,"liab":6429.3,"equity":2212.2,"rev":5773.3,"gp":739.8,"op":313.4,"np":279.0,"cfo":-591.8,"cfi":-39.6,"capex_ppe":78.5,"capex_intan":0.6,"cff":233.7},"2017":{"ca":4352.9,"cash":901.2,"nca":3824.8,"asset":8177.7,"cl":6314.8,"ncl":862.6,"liab":7177.4,"equity":1000.2,"rev":4701.5,"gp":469.9,"op":107.1,"np":-60.2,"cfo":664.4,"cfi":-401.1,"capex_ppe":141.3,"capex_intan":1.7,"cff":-412.4},"2016":{"cash":1051.4,"asset":8302.3,"equity":1072.6,"liab":7229.6,"rev":5298.5,"op":41.2,"capex_ppe":90.8,"capex_intan":1.3,"np":-279.5}},"quarter":{"25Q1":{"asset":9464.7,"ca":5252.0,"cash":443.3,"nca":4212.7,"equity":2853.4,"cl":5929.5,"liab":6611.3,"ncl":681.8,"op":154.5,"gp":288.2,"np":105.5,"pretax":103.0,"rev":1391.4,"cff":-376.5,"cfi":-34.1,"capex_intan":15.4,"capex_ppe":18.0,"cfo":-461.6},"25Q2":{"asset":10548.0,"ca":6358.4,"cash":1090.2,"nca":4189.6,"equity":3150.5,"cl":6701.2,"liab":7397.5,"ncl":696.3,"op":333.5,"gp":463.7,"np":297.1,"pretax":301.3,"rev":2136.6,"cff":95.6,"cfi":-39.8,"capex_intan":7.3,"capex_ppe":20.8,"cfo":595.3},"25Q3":{"asset":10977.4,"ca":6717.1,"cash":1671.5,"nca":4260.3,"equity":3306.0,"cl":6962.6,"liab":7671.5,"ncl":708.9,"op":154.3,"gp":318.0,"np":140.5,"pretax":141.5,"rev":1920.7,"cff":74.0,"cfi":-83.6,"capex_intan":43.3,"capex_ppe":22.9,"cfo":583.2},"25Q4":{"asset":11575.4,"ca":7270.8,"cash":1641.3,"nca":4304.6,"equity":3429.7,"cl":7449.2,"liab":8145.6,"ncl":696.4,"op":53.7,"gp":249.4,"np":146.4,"pretax":72.6,"rev":2444.8,"cff":68.5,"cfi":-108.6,"capex_intan":24.5,"capex_ppe":37.4,"cfo":11.8},"26Q1":{"asset":12095.4,"ca":7745.1,"cash":1102.7,"nca":4350.3,"equity":3604.1,"cl":7796.1,"liab":8491.3,"ncl":695.1,"op":175.0,"gp":321.5,"np":166.7,"pretax":160.0,"rev":1890.1,"cff":336.9,"cfi":-120.4,"capex_intan":0.7,"capex_ppe":41.2,"cfo":-763.3}}},"ofs":{"annual":{"2025":{"asset":11257.3,"ca":6989.7,"cash":1528.0,"nca":4267.7,"equity":3180.2,"cl":7394.2,"liab":8077.1,"ncl":683.0,"op":647.5,"gp":1152.3,"np":645.7,"pretax":568.8,"rev":7448.2,"cff":-126.9,"cfi":-264.9,"capex_intan":90.5,"capex_ppe":98.0,"cfo":694.8},"2024":{"asset":9376.9,"ca":5271.5,"cash":1226.5,"nca":4105.4,"equity":2575.2,"cl":6172.2,"liab":6801.7,"ncl":629.5,"op":373.7,"gp":830.4,"np":226.4,"pretax":168.8,"rev":6879.6,"cff":229.1,"cfi":-146.2,"capex_intan":91.8,"capex_ppe":88.9,"cfo":366.0},"2023":{"asset":8798.7,"ca":4736.4,"cash":775.5,"nca":4062.4,"equity":2470.4,"cl":5713.9,"liab":6328.4,"ncl":614.4,"op":165.6,"gp":562.9,"np":37.8,"pretax":53.5,"rev":5969.4,"cff":86.8,"cfi":35.8,"capex_intan":72.5,"capex_ppe":86.6,"cfo":-189.6},"2022":{"ca":4529.3,"cash":842.5,"nca":3846.2,"asset":8375.5,"cl":5350.7,"ncl":522.9,"liab":5873.6,"equity":2501.8,"rev":5147.4,"gp":240.9,"op":-118.9,"pretax":-318.6,"np":-280.9,"cfo":238.6,"cfi":-151.6,"capex_ppe":120.8,"capex_intan":4.9,"cff":-271.6},"2021":{"ca":4058.7,"cash":1027.2,"nca":4172.0,"asset":8230.7,"cl":4851.7,"ncl":628.3,"liab":5480.0,"equity":2750.8,"rev":4582.8,"gp":297.2,"op":2.4,"pretax":-56.3,"np":-20.3,"cfo":183.5,"cfi":-99.7,"capex_ppe":118.8,"capex_intan":10.9,"cff":-161.3},"2020":{"ca":4297.4,"cash":1104.7,"nca":3696.2,"asset":7993.6,"cl":4759.1,"ncl":626.6,"liab":5385.7,"equity":2607.9,"rev":5577.7,"gp":428.1,"op":115.2,"pretax":236.0,"np":260.5,"cfo":567.4,"cfi":302.7,"capex_ppe":90.9,"capex_intan":4.0,"cff":-378.7},"2019":{"ca":4288.0,"cash":613.3,"nca":3882.8,"asset":8170.8,"cl":3453.9,"ncl":2353.1,"liab":5807.0,"equity":2363.8,"rev":5774.9,"gp":533.5,"op":251.1,"pretax":96.1,"np":159.4,"cfo":701.4,"cfi":141.9,"capex_ppe":86.8,"capex_intan":1.7,"cff":-723.7},"2018":{"ca":4969.9,"cash":493.7,"nca":3700.4,"asset":8670.3,"cl":3492.8,"ncl":2930.6,"liab":6423.4,"equity":2246.9,"rev":5664.9,"gp":672.8,"op":284.2,"np":248.4,"cfo":-590.0,"cfi":-35.9,"capex_ppe":74.9,"capex_intan":0.6,"cff":233.7},"2017":{"ca":4379.4,"cash":885.9,"nca":3821.2,"asset":8200.7,"cl":6273.2,"ncl":862.5,"liab":7135.7,"equity":1065.0,"rev":4567.3,"gp":461.9,"op":162.1,"np":-11.9,"cfo":672.2,"cfi":-400.4,"capex_ppe":140.8,"capex_intan":1.7,"cff":-412.4},"2016":{"cash":1026.5,"asset":8213.8,"equity":1090.9,"liab":7122.8,"rev":5298.5,"op":41.2,"capex_ppe":90.8,"capex_intan":1.3,"np":-261.3}},"quarter":{"25Q1":{"asset":9156.2,"ca":4972.5,"cash":365.4,"nca":4183.7,"equity":2651.6,"cl":5830.0,"liab":6504.6,"ncl":674.6,"op":147.1,"gp":249.9,"np":99.5,"pretax":97.2,"rev":1283.6,"cff":-373.7,"cfi":-33.8,"capex_intan":15.4,"capex_ppe":17.8,"cfo":-453.6},"25Q2":{"asset":10216.2,"ca":6061.5,"cash":1011.3,"nca":4154.7,"equity":2931.3,"cl":6601.9,"liab":7284.9,"ncl":683.0,"op":305.9,"gp":408.1,"np":274.3,"pretax":276.2,"rev":2032.7,"cff":98.3,"cfi":-39.4,"capex_intan":7.3,"capex_ppe":20.3,"cfo":588.7},"25Q3":{"asset":10617.6,"ca":6389.9,"cash":1562.1,"nca":4227.7,"equity":3065.4,"cl":6854.5,"liab":7552.2,"ncl":697.7,"op":142.3,"gp":276.8,"np":126.9,"pretax":127.0,"rev":1823.6,"cff":77.0,"cfi":-83.3,"capex_intan":43.3,"capex_ppe":22.6,"cfo":552.0},"25Q4":{"asset":11257.3,"ca":6989.7,"cash":1528.0,"nca":4267.7,"equity":3180.2,"cl":7394.2,"liab":8077.1,"ncl":683.0,"op":52.3,"gp":217.5,"np":145.0,"pretax":68.5,"rev":2308.4,"cff":71.5,"cfi":-108.4,"capex_intan":24.5,"capex_ppe":37.2,"cfo":7.7},"26Q1":{"asset":11755.1,"ca":7439.6,"cash":983.0,"nca":4315.5,"equity":3332.0,"cl":7739.5,"liab":8423.1,"ncl":683.6,"op":164.8,"gp":278.4,"np":156.4,"pretax":149.7,"rev":1779.7,"cff":339.9,"cfi":-120.4,"capex_intan":0.7,"capex_ppe":41.2,"cfo":-767.7}}},"market":"kr","est":{"2026":{"rev":9494.0,"op":1004.0,"np":815.0}}}