{"cfs":{"annual":{"2025":{"asset":94087.3,"equity":51951.7,"liab":42135.6,"np":2684.1,"pretax":3743.8,"op":3757.0,"cash":1287.1,"cff":-2201.7,"cfi":-2094.7,"capex_intan":601.6,"capex_ppe":140.8,"cfo":3872.3}},"quarter":{"25Q1":{"asset":95387.1,"equity":50358.7,"liab":45028.4,"np":193.7,"pretax":257.0,"op":272.7,"cash":1546.6,"cff":-46.0,"cfi":-1650.3,"capex_intan":501.3,"capex_ppe":70.8,"cfo":1511.9},"25Q2":{"asset":94373.6,"equity":52049.5,"liab":42324.1,"np":654.2,"pretax":851.4,"op":845.5,"cash":1413.2,"cff":-2046.7,"cfi":1545.6,"capex_intan":17.8,"capex_ppe":21.1,"cfo":431.9},"25Q3":{"asset":93935.6,"equity":51865.9,"liab":42069.7,"np":618.4,"pretax":809.8,"op":809.5,"cash":1305.9,"cff":-64.6,"cfi":-446.0,"capex_intan":19.9,"capex_ppe":2.8,"cfo":374.3},"25Q4":{"asset":94087.3,"equity":51951.7,"liab":42135.6,"np":1217.7,"pretax":1825.6,"op":1829.4,"cash":1287.1,"cff":-44.4,"cfi":-1544.0,"capex_intan":62.6,"capex_ppe":46.1,"cfo":1554.2},"26Q1":{"asset":94586.0,"equity":49850.9,"liab":44735.1,"np":574.9,"pretax":855.1,"op":934.7,"cash":1232.1,"cff":-46.5,"cfi":-740.1,"capex_intan":15.2,"capex_ppe":2.5,"cfo":696.3}}},"ofs":{"annual":{"2025":{"asset":93738.3,"equity":51740.2,"liab":41998.1,"np":2642.4,"pretax":3693.5,"op":3713.3,"cash":1247.7,"cff":-2182.2,"cfi":-2084.3,"capex_intan":592.8,"capex_ppe":139.4,"cfo":3816.9}},"quarter":{"25Q1":{"asset":95089.4,"equity":50184.5,"liab":44904.9,"np":190.7,"pretax":252.7,"op":263.8,"cash":1527.5,"cff":-41.1,"cfi":-1639.5,"capex_intan":499.9,"capex_ppe":69.8,"cfo":1491.0},"25Q2":{"asset":94071.0,"equity":51873.8,"liab":42197.2,"np":652.0,"pretax":849.2,"op":842.3,"cash":1388.1,"cff":-2041.6,"cfi":1544.7,"capex_intan":15.8,"capex_ppe":20.7,"cfo":421.6},"25Q3":{"asset":93619.6,"equity":51684.3,"liab":41935.4,"np":612.9,"pretax":804.2,"op":800.5,"cash":1281.2,"cff":-59.6,"cfi":-446.0,"capex_intan":18.1,"capex_ppe":2.7,"cfo":369.6},"25Q4":{"asset":93738.3,"equity":51740.2,"liab":41998.1,"np":1186.8,"pretax":1787.4,"op":1806.7,"cash":1247.7,"cff":-39.9,"cfi":-1543.6,"capex_intan":59.1,"capex_ppe":46.1,"cfo":1534.7},"26Q1":{"asset":94239.3,"equity":49632.5,"liab":44606.9,"np":568.7,"pretax":846.4,"op":923.6,"cash":1191.7,"cff":-41.4,"cfi":-743.3,"capex_intan":15.2,"capex_ppe":2.4,"cfo":693.6}}},"market":"kr","est":{}}