{"annual":{"2025":{"asset":9325.6,"ca":4834.5,"cash":706.0,"nca":4491.1,"equity":3568.6,"cl":4565.8,"liab":5757.0,"ncl":1191.2,"op":276.9,"gp":956.6,"np":242.1,"pretax":310.8,"rev":9453.6,"cff":737.0,"cfi":-521.4,"capex_intan":0.7,"capex_ppe":944.6,"cfo":143.8},"2024":{"asset":7741.1,"ca":4335.4,"cash":323.1,"nca":3405.7,"equity":3173.1,"cl":4245.0,"liab":4568.0,"ncl":323.0,"op":271.8,"gp":907.8,"np":74.5,"pretax":142.4,"rev":9097.2,"cff":24.8,"cfi":-143.7,"capex_intan":4.3,"capex_ppe":314.5,"cfo":9.2},"2023":{"asset":6923.4,"ca":3836.7,"cash":412.8,"nca":3086.8,"equity":3075.7,"cl":3496.7,"liab":3847.7,"ncl":351.0,"op":298.7,"gp":975.6,"np":200.6,"pretax":283.6,"rev":8337.0,"cff":407.2,"cfi":-678.5,"capex_ppe":333.3,"cfo":361.0},"2022":{"ca":3316.3,"cash":328.1,"nca":2962.2,"asset":6278.5,"cl":3556.0,"ncl":577.6,"liab":4133.6,"equity":2144.9,"rev":7934.2,"gp":898.8,"op":320.6,"pretax":294.6,"np":239.2,"cfo":-29.1,"cfi":-569.2,"capex_ppe":475.9,"capex_intan":0.5,"cff":589.0},"2021":{"ca":2739.5,"cash":334.9,"nca":2432.5,"asset":5172.0,"cl":2842.5,"ncl":374.1,"liab":3216.6,"equity":1955.4,"rev":7374.9,"gp":916.1,"op":439.5,"pretax":425.9,"np":326.9,"cfo":169.7,"cfi":-117.1,"capex_ppe":302.8,"cff":-49.2},"2020":{"ca":2027.1,"cash":318.0,"nca":2087.7,"asset":4114.8,"cl":2124.8,"ncl":368.8,"liab":2493.6,"equity":1621.2,"rev":4930.7,"gp":453.6,"op":148.2,"pretax":106.8,"np":88.8,"cfo":63.7,"cfi":-122.2,"capex_ppe":144.1,"capex_intan":0.1,"cff":174.1},"2019":{"ca":1436.0,"cash":215.3,"nca":2050.8,"asset":3486.8,"cl":1670.9,"ncl":477.9,"liab":2148.8,"equity":1338.0,"rev":4536.5,"gp":482.1,"op":103.5,"pretax":80.2,"np":52.8,"cfo":64.5,"cfi":-150.2,"capex_ppe":155.8,"capex_intan":0.0,"cff":171.2},"2018":{"ca":1339.3,"cash":124.9,"nca":1964.9,"asset":3304.3,"cl":1516.2,"ncl":579.6,"liab":2095.8,"equity":1208.5,"rev":4370.5,"gp":489.1,"op":126.6,"pretax":56.0,"np":40.3,"cfo":182.9,"cfi":-209.5,"capex_ppe":165.8,"cff":-48.0},"2017":{"ca":1491.2,"cash":200.6,"nca":1853.6,"asset":3344.8,"cl":1638.8,"ncl":525.0,"liab":2163.8,"equity":1181.0,"rev":4647.7,"gp":564.7,"op":178.9,"pretax":168.6,"np":123.8,"cfo":242.7,"cfi":-85.6,"capex_ppe":87.4,"cff":-176.4},"2016":{"ca":1494.6,"cash":226.1,"nca":1893.5,"asset":3388.1,"cl":1779.6,"ncl":602.4,"liab":2382.1,"equity":1006.0,"rev":3946.1,"gp":494.4,"op":121.2,"pretax":30.2,"np":10.0,"cfo":89.3,"cfi":-72.2,"capex_ppe":144.1,"capex_intan":2.8,"cff":59.2}},"market":"kr","est":{}}