{"annual":{"2025":{"asset":5494.5,"ca":1605.1,"cash":226.3,"nca":3889.4,"equity":4728.3,"cl":435.3,"liab":766.3,"ncl":330.9,"op":-196.3,"gp":-53.3,"np":-191.3,"pretax":-189.2,"rev":3673.9,"cff":-641.8,"cfi":-137.5,"capex_intan":3.7,"capex_ppe":216.9,"cfo":54.6},"2024":{"asset":6234.9,"ca":2205.1,"cash":954.7,"nca":4029.7,"equity":4979.1,"cl":915.2,"liab":1255.8,"ncl":340.6,"op":-0.3,"gp":130.9,"np":204.6,"pretax":27.0,"rev":4004.8,"cff":-207.6,"cfi":-169.1,"capex_intan":1.1,"capex_ppe":365.2,"cfo":530.8},"2023":{"asset":6099.1,"ca":1827.2,"cash":787.6,"nca":4271.9,"equity":4701.6,"cl":487.4,"liab":1397.5,"ncl":910.1,"op":-167.1,"gp":-6.6,"np":-140.4,"pretax":-148.9,"rev":4375.9,"cff":-309.8,"cfi":311.2,"capex_intan":3.6,"capex_ppe":268.4,"cfo":360.2},"2022":{"ca":2718.8,"cash":424.4,"nca":4030.0,"asset":6748.7,"cl":892.1,"ncl":1017.4,"liab":1909.6,"equity":4839.2,"rev":6994.1,"gp":798.7,"op":628.8,"pretax":713.9,"np":454.5,"cfo":949.1,"cfi":-1061.7,"capex_ppe":537.7,"capex_intan":14.4,"cff":-159.4},"2021":{"ca":2496.5,"cash":688.6,"nca":3997.5,"asset":6494.0,"cl":952.1,"ncl":1283.3,"liab":2235.4,"equity":4258.6,"rev":6411.1,"gp":825.2,"op":665.0,"pretax":669.2,"np":551.0,"cfo":1015.5,"cfi":-560.1,"capex_ppe":242.1,"capex_intan":5.0,"cff":-353.6},"2020":{"ca":1748.7,"cash":565.8,"nca":4116.8,"asset":5865.4,"cl":652.8,"ncl":1664.4,"liab":2317.2,"equity":3548.2,"rev":5730.8,"gp":512.7,"op":342.8,"pretax":208.9,"np":176.1,"cfo":833.4,"cfi":172.3,"capex_ppe":252.3,"capex_intan":8.3,"cff":-1059.1},"2019":{"ca":2267.3,"cash":623.9,"nca":4345.0,"asset":6612.3,"cl":3201.1,"ncl":252.8,"liab":3453.9,"equity":3158.4,"rev":5889.4,"gp":531.4,"op":390.8,"pretax":264.0,"np":208.2,"cfo":795.3,"cfi":-444.7,"capex_ppe":400.2,"capex_intan":10.6,"cff":-60.3},"2018":{"ca":1771.6,"cash":333.1,"nca":4502.1,"asset":6273.7,"cl":971.8,"ncl":2424.6,"liab":3396.4,"equity":2877.2,"rev":4578.5,"gp":467.7,"op":336.9,"pretax":192.8,"np":132.8,"cfo":363.3,"cfi":-390.6,"capex_ppe":359.4,"capex_intan":11.4,"cff":-346.2},"2017":{"ca":1772.5,"cash":697.3,"nca":4556.7,"asset":6329.2,"cl":1080.2,"ncl":2552.8,"liab":3633.0,"equity":2696.2,"rev":4495.6,"gp":388.9,"op":254.6,"pretax":111.3,"np":98.7,"cfo":844.0,"cfi":-886.1,"capex_ppe":774.1,"capex_intan":4.9,"cff":-238.9},"2016":{"ca":2248.7,"cash":1024.4,"nca":4513.0,"asset":6761.7,"cl":1398.8,"ncl":2647.2,"liab":4046.0,"equity":2715.8,"rev":4292.1,"gp":297.6,"op":148.1,"pretax":93.9,"np":75.8,"cfo":442.5,"cfi":-52.0,"capex_ppe":223.6,"capex_intan":11.0,"cff":-566.2}},"market":"kr","est":{"2026":{"rev":5326.0,"op":60.0,"np":63.0}}}