{"annual":{"2025":{"asset":10422.6,"ca":417.8,"cash":248.6,"nca":10004.8,"equity":3630.6,"cl":2098.3,"liab":6792.0,"ncl":4693.8,"op":150.1,"gp":263.5,"np":29.9,"pretax":29.9,"cff":20.1,"cfi":-170.3,"cfo":64.2},"2024":{"asset":8529.6,"ca":397.0,"cash":217.9,"nca":8132.6,"equity":2979.7,"cl":5075.9,"liab":5549.9,"ncl":474.1,"op":103.6,"gp":202.1,"np":31.1,"pretax":31.1,"cff":-72.5,"cfi":-20.1,"cfo":77.6},"2023":{"asset":8603.2,"ca":337.0,"cash":191.2,"nca":8266.2,"equity":3090.5,"cl":1250.1,"liab":5512.7,"ncl":4262.6,"op":107.8,"gp":209.2,"np":35.1,"pretax":35.1,"cff":-111.5,"cfi":10.6,"cfo":67.5},"2022":{"ca":447.4,"cash":343.4,"nca":8242.9,"asset":8690.4,"cl":629.2,"ncl":4882.2,"liab":5511.3,"equity":3179.0,"gp":200.1,"op":103.2,"pretax":15.1,"np":15.1,"cfo":71.7,"cfi":-1023.8,"cff":1082.0},"2021":{"ca":243.8,"cash":181.8,"nca":7378.7,"asset":7622.5,"cl":62.1,"ncl":4270.1,"liab":4332.3,"equity":3290.2,"gp":167.6,"op":50.9,"pretax":25.0,"np":25.0,"cfo":-41.4,"cfi":-1317.0,"cff":1429.7}},"market":"kr","est":{}}