{"annual":{"2025":{"asset":10902.4,"ca":1001.8,"cash":269.6,"nca":9900.7,"equity":3526.6,"cl":5060.5,"liab":7375.9,"ncl":2315.4,"op":237.4,"np":59.2,"pretax":59.2,"rev":320.8,"cff":-174.8,"cfi":43.0,"cfo":173.5},"2024":{"asset":9684.4,"ca":629.3,"cash":404.1,"nca":9055.1,"equity":3278.3,"cl":862.0,"liab":6406.1,"ncl":5544.1,"op":119.2,"np":102.7,"pretax":102.7,"rev":180.6,"cff":134.0,"cfi":31.6,"cfo":90.7},"2023":{"asset":6215.1,"ca":369.8,"cash":173.9,"nca":5845.3,"equity":2596.2,"cl":797.6,"liab":3618.9,"ncl":2821.2,"op":106.5,"np":53.1,"pretax":53.1,"rev":164.7,"cff":419.1,"cfi":-582.3,"cfo":102.4},"2022":{"ca":452.3,"cash":190.4,"nca":5356.9,"asset":5809.2,"cl":2017.9,"ncl":1122.9,"liab":3140.8,"equity":2668.4,"rev":149.3,"op":94.5,"pretax":54.4,"np":54.4,"cfo":97.2,"cfi":-30.0,"cff":-87.3},"2021":{"ca":502.5,"cash":235.6,"nca":5423.0,"asset":5925.5,"cl":151.5,"ncl":3056.1,"liab":3207.7,"equity":2717.8,"rev":105.8,"op":56.6,"pretax":16.5,"np":16.5,"cfo":-43.9,"cfi":-1721.4,"cff":1855.5}},"market":"kr","est":{}}