{"annual":{"2025":{"asset":780.3,"ca":401.5,"cash":147.9,"nca":378.7,"equity":528.1,"cl":233.8,"liab":252.2,"ncl":18.4,"op":-123.1,"gp":21.4,"np":-271.8,"pretax":-273.3,"rev":51.5,"cff":3.9,"cfi":9.2,"capex_ppe":1.4,"cfo":-111.1},"2024":{"asset":705.6,"ca":322.7,"cash":241.9,"nca":382.9,"equity":486.4,"cl":199.2,"liab":219.2,"ncl":20.1,"op":-133.8,"gp":25.6,"np":-80.9,"pretax":-80.0,"rev":45.9,"cff":198.6,"cfi":-42.7,"capex_ppe":2.6,"cfo":-97.0},"2023":{"asset":578.0,"ca":216.0,"cash":179.1,"nca":362.0,"equity":528.8,"cl":27.2,"liab":49.1,"ncl":22.0,"op":-105.6,"gp":38.3,"np":-100.4,"pretax":-102.1,"rev":67.9,"cff":176.4,"cfi":29.0,"capex_ppe":2.1,"cfo":-81.6}},"market":"kr","est":{"2026":{"rev":61.0,"op":-122.0,"np":-118.0}}}